setup.cfg
setup.py
tabxlsx.md
tabxlsx.py
tabxlsx.tests.py
tabxlsx.txt
tabxlsx.egg-info/PKG-INFO
tabxlsx.egg-info/SOURCES.txt
tabxlsx.egg-info/dependency_links.txt
tabxlsx.egg-info/requires.txt
tabxlsx.egg-info/top_level.txt