Metadata-Version: 2.1
Name: tabxlsx
Version: 1.1.3352
Summary: tabXLSX reads and writes simple Excel xlsx files. Single script not depending on other libraries.
Home-page: https://github.com/gdraheim/timetrack-odoo
Author: Guido U. Draheim
Author-email: Guido.Draheim@gmx.de
License: APL
Platform: UNKNOWN
Provides-Extra: tabxlsx
